{
  "act_version": "0.1",
  "id": "sku-000041",
  "type": "product",
  "title": "Riverbend Jacket — Charcoal",
  "summary": "Riverbend jacket in charcoal; built in Canada for daily use.",
  "summary_source": "author",
  "parent": "catalog",
  "etag": "s256:7v3JBryTNY0KZTl_nz_hh1",
  "tokens": {
    "summary": 10,
    "body": 83
  },
  "content": [
    {
      "type": "prose",
      "format": "markdown",
      "text": "# Riverbend Jacket — Charcoal\n\nBuilt for daily wear and refinishing. The Riverbend Jacket — Charcoal is designed for the long haul, with apparel-grade materials and a quiet, considered fit and finish.\n\n## Highlights\n\n- Crafted in Canada.\n- Repairable construction with serviceable parts.\n- Backed by a one-year materials warranty.\n\n## Care\n\nCondition every 60 days for best results. Spot-clean only; avoid harsh detergents. Store in a cool, dry place out of direct sunlight.",
      "metadata": {
        "extracted_via": "adapter"
      }
    },
    {
      "type": "data",
      "format": "json",
      "text": "{\"weight_g\":1198,\"materials\":{\"upper\":\"aluminum housing\",\"sole\":\"memory foam\",\"lining\":\"oxford weave\"},\"care\":\"wipe with a damp cloth\",\"made_in\":\"Canada\",\"sizes_us\":[8,8.5,9,9.5,10,10.5,11,11.5,12]}",
      "value": {
        "weight_g": 1198,
        "materials": {
          "upper": "aluminum housing",
          "sole": "memory foam",
          "lining": "oxford weave"
        },
        "care": "wipe with a damp cloth",
        "made_in": "Canada",
        "sizes_us": [
          8,
          8.5,
          9,
          9.5,
          10,
          10.5,
          11,
          11.5,
          12
        ]
      },
      "metadata": {
        "extracted_via": "adapter"
      }
    }
  ],
  "related": [
    {
      "id": "sku-000009",
      "relation": "see-also"
    },
    {
      "id": "sku-000017",
      "relation": "see-also"
    },
    {
      "id": "sku-000025",
      "relation": "see-also"
    },
    {
      "id": "sku-000033",
      "relation": "see-also"
    },
    {
      "id": "sku-000049",
      "relation": "see-also"
    },
    {
      "id": "sku-000057",
      "relation": "see-also"
    },
    {
      "id": "sku-000065",
      "relation": "see-also"
    },
    {
      "id": "sku-000073",
      "relation": "see-also"
    }
  ],
  "metadata": {
    "schema_org_type": "Product",
    "tags": [
      "apparel",
      "made-in-canada",
      "charcoal"
    ],
    "source": {
      "adapter": "act-catalog",
      "source_id": "sku-000041"
    }
  }
}