{
  "_fixture": "PRD-104 positive — Pattern 2, per-locale manifests via manifest_url_template",
  "_satisfies": ["PRD-104-R1", "PRD-104-R2", "PRD-104-R4", "PRD-104-R6"],
  "act_version": "0.1",
  "site": { "name": "Acme", "locale": "en-US" },
  "conformance": { "level": "plus" },
  "delivery": "static",
  "index_url": "/act/index.json",
  "index_ndjson_url": "/act/index.ndjson",
  "node_url_template": "/act/n/{id}.json",
  "subtree_url_template": "/act/sub/{id}.json",
  "search_url_template": "/act/search?q={query}&locale={locale}",
  "locales": {
    "default": "en-US",
    "available": ["en-US", "es-ES", "de-DE", "ja-JP"],
    "manifest_url_template": "/{locale}/.well-known/act.json"
  },
  "capabilities": {
    "etag": true,
    "subtree": true,
    "ndjson_index": true,
    "search": { "template_advertised": true }
  }
}
